{
  "db_name": "PostgreSQL",
  "query": "SELECT is_instance_admin FROM users WHERE id = $1",
  "describe": {
    "columns": [
      {
        "ordinal": 0,
        "name": "is_instance_admin",
        "type_info": "Bool",
        "origin": {
          "Table": {
            "table": "users",
            "name": "is_instance_admin"
          }
        }
      }
    ],
    "parameters": {
      "Left": [
        "Uuid"
      ]
    },
    "nullable": [
      false
    ]
  },
  "hash": "09b31423857d5975f6b2130c199f90a9c45e8761deb1fbef72986dda3b09a2e7"
}
